scons_tool_texas-0.2.0-py3.8-nspkg.pth
sconstool/texas/TeXASCommon.py
sconstool/texas/TeXASDist.py
sconstool/texas/TeXASDoc.py
sconstool/texas/__init__.py
sconstool/texas/about.py
scons_tool_texas-0.2.0.dist-info/METADATA
scons_tool_texas-0.2.0.dist-info/WHEEL
scons_tool_texas-0.2.0.dist-info/namespace_packages.txt
scons_tool_texas-0.2.0.dist-info/top_level.txt
scons_tool_texas-0.2.0.dist-info/RECORD
