Metadata-Version: 2.1
Name: scons-tool-texas
Version: 0.2.0
Summary: TeX Automated with SCons
Home-page: https://github.com/ptomulik/scons-tool-texas
Author: Paweł Tomulik
Author-email: ptomulik@meil.pw.edu.pl
License: UNKNOWN
Platform: UNKNOWN
Requires-Python: >=2.7
Requires-Dist: scons-tool-util (>=0.1.10)
Requires-Dist: scons-tool-kpsewhich (>=0.1.1)
Requires-Dist: scons-tool-dvipdfm (>=0.1.0)
Requires-Dist: scons-tool-archives (>=0.1.1)
